odoo/addons/crm_stage_multi_team/README.rst
odoo/addons/crm_stage_multi_team/__init__.py
odoo/addons/crm_stage_multi_team/__manifest__.py
odoo/addons/crm_stage_multi_team/hooks.py
odoo/addons/crm_stage_multi_team/i18n/crm_stage_multi_team.pot
odoo/addons/crm_stage_multi_team/i18n/es.po
odoo/addons/crm_stage_multi_team/i18n/it.po
odoo/addons/crm_stage_multi_team/models/__init__.py
odoo/addons/crm_stage_multi_team/models/crm_lead.py
odoo/addons/crm_stage_multi_team/models/crm_stage.py
odoo/addons/crm_stage_multi_team/readme/CONFIGURE.md
odoo/addons/crm_stage_multi_team/readme/CONTRIBUTORS.md
odoo/addons/crm_stage_multi_team/readme/DESCRIPTION.md
odoo/addons/crm_stage_multi_team/readme/USAGE.md
odoo/addons/crm_stage_multi_team/static/description/icon.png
odoo/addons/crm_stage_multi_team/static/description/index.html
odoo/addons/crm_stage_multi_team/tests/__init__.py
odoo/addons/crm_stage_multi_team/tests/test_crm_stage_multi_team.py
odoo/addons/crm_stage_multi_team/views/crm_lead_views.xml
odoo/addons/crm_stage_multi_team/views/crm_stage_views.xml
odoo_addon_crm_stage_multi_team-18.0.1.0.1.dist-info/METADATA
odoo_addon_crm_stage_multi_team-18.0.1.0.1.dist-info/WHEEL
odoo_addon_crm_stage_multi_team-18.0.1.0.1.dist-info/top_level.txt
odoo_addon_crm_stage_multi_team-18.0.1.0.1.dist-info/RECORD
