Metadata-Version: 2.1
Name: odoo-addon-crm_stage_multi_team
Version: 18.0.1.0.1
Requires-Python: >=3.10
Requires-Dist: odoo==18.0.*
Summary: Allows multiple teams in crm stage
Home-page: https://github.com/OCA/crm
License: AGPL-3
Author: Tecnativa, Odoo Community Association (OCA), Odoo SA
Author-email: support@odoo-community.org
Classifier: Programming Language :: Python
Classifier: Framework :: Odoo
Classifier: Framework :: Odoo :: 18.0
Classifier: License :: OSI Approved :: GNU Affero General Public License v3
Classifier: Development Status :: 3 - Alpha
